{
  "module": {
    "name": "FuncEncapsulation",
    "type": "feature",
    "description": "$string:module_desc",
    "mainElement": "FuncEncapsulationAbility",
    "deviceTypes": [
      "phone",
      "tablet",
      "2in1"
    ],
    "deliveryWithInstall": true,
    "installationFree": false,
    "pages": "$profile:main_pages",
    "abilities": [
      {
        "name": "FuncEncapsulationAbility",
        "srcEntry": "./ets/funcencapsulationability/FuncEncapsulationAbility.ets",
        "description": "$string:FuncEncapsulationAbility_desc",
        "icon": "$media:layered_image",
        "label": "$string:FuncEncapsulationAbility_label",
        "startWindowIcon": "$media:startIcon",
        "startWindowBackground": "$color:start_window_background",
        "exported": true
      }
    ]
  }
}